{
    "output":  "C:\\Users\\ftass\\OneDrive\\Bureau\\RETRODEX VERSION OK\\retrodex_v2_checkpoint_20260313_1722\\prototype_v2\\retrodeck_assets\\duck_tales_nintendo_entertainment_system\\sprite.png",
    "opaque_ratio":  0.3685,
    "source":  "C:\\Users\\ftass\\OneDrive\\Bureau\\RETRODEX VERSION OK\\retrodex_v2_checkpoint_20260313_1722\\prototype_v2\\retrodeck_assets\\_cache\\source_images\\wikipedia_en_5_54_scrooge_mcduck_png.png",
    "bbox":  {
                 "y":  3,
                 "width":  26,
                 "height":  42,
                 "x":  11
             },
    "colors_used":  [
                        "#8BAC0F",
                        "#9BBC0F",
                        "#306230",
                        "#0F380F"
                    ],
    "work_size":  48,
    "canvas_size":  128
}
